devpi_remote_user/__init__.py
devpi_remote_user/main.py
devpi_remote_user-0.3.dist-info/LICENSE
devpi_remote_user-0.3.dist-info/METADATA
devpi_remote_user-0.3.dist-info/WHEEL
devpi_remote_user-0.3.dist-info/entry_points.txt
devpi_remote_user-0.3.dist-info/top_level.txt
devpi_remote_user-0.3.dist-info/RECORD
