Metadata-Version: 2.1
Name: devpi-remote-user
Version: 0.3
Summary: devpi-server plugin  - Accept requests based on the X-Remote-User header (provided by nginx for example)   Example nginx directive: `proxy_set_header X-Remote-User $remote_user;` - Do not check any credential and give the user the 'remote_user' group. 
Home-page: https://github.com/Polyconseil/devpi-remote_user
Author: Polyconseil
Author-email: opensource+devpi-remote_user@polyconseil.fr
License: MIT
Keywords: devpi plugin
Platform: UNKNOWN
Classifier: Intended Audience :: Developers
Classifier: Intended Audience :: System Administrators
Classifier: License :: OSI Approved :: BSD License
Classifier: Natural Language :: English
Classifier: Programming Language :: Python
License-File: LICENSE
Requires-Dist: devpi-server (>=6)
